{
  "logIn": [
    {
      "id": 1,
      "mail": "pizza@pizza.com",
      "password": "Pizza"
    }
  ],
  "pizza": [
    {
      "id": 1,
      "name": "Royal",
      "image": "https://img.cuisineaz.com/660x660/2013/12/20/i95731-pizza-royale.jpg",
      "price": 9.50,
      "isnormal": true,
      "base": "tomate",
      "ingredient": ["jambon","champignon","oeuf","mozzarela"]
    },
    {
      "id": 2,
      "name": "4 fromages",
      "image": "https://static.750g.com/images/1200-630/40aa1a90bb47bba1a235eeb66eb11e4b/gettyimages-954475908.jpg",
      "price": 12,
      "isnormal": true,
      "base": "tomate",
      "ingredient": ["roquefort","parmesan","chèvre","mozzarela"]
    },
    {
      "id": 3,
      "name": "Poulet curry",
      "image": "https://fac.img.pmdstatic.net/fit/http.3A.2F.2Fprd2-bone-image.2Es3-website-eu-west-1.2Eamazonaws.2Ecom.2Ffac.2F2018.2F07.2F30.2F0815bb38-cd3e-4378-8e9f-2afbed8af90d.2Ejpeg/750x562/quality/80/crop-from/center/cr/wqkgUGFyw6kgLyBTdWNyw6kgU2Fsw6kgLyBGZW1tZSBBY3R1ZWxsZQ%3D%3D/pizza-au-poulet-et-curry.jpeg",
      "price": 11.50,
      "isnormal": true,
      "base": "crème",
      "ingredient": ["Poulet","Curry","Oignon","mozzarela"]
    },
    {
      "id": 4,
      "name": "Chorizo",
      "image": "https://img.cuisineaz.com/660x660/2016/05/13/i71494-pizza-au-chorizo-poivron-et-tomate-a-ma-facon.webp",
      "price": 10.50,
      "isnormal": true,
      "base": "tomate",
      "ingredient": ["chorizo","poivron","Oignon","mozzarela"]
    },
    {
      "id": 5,
      "name": "Hawaïenne",
      "image": "https://dam.savencia.com/api/wedia/dam/transform/fix635d9eidk6joz8fkkfaaao74moc5jo1uzhme/800?t=resize&width=800",
      "price": 1,
      "isnormal": true,
      "base": "tomate",
      "ingredient": ["annanas","oignon","jambon","mozzarela"]
    },
    {
      "id": 6,
      "name": "Margherita",
      "image": "https://assets.afcdn.com/recipe/20200206/107152_w1024h1024c1cx176cy267.webp",
      "price": 12,
      "isnormal": true,
      "base": "tomate",
      "ingredient": ["parmesan","basilic","mozzarela"]
    }
  ],
  "boisson": [
    {
      "id": 1,
      "name": "Pepsi",
      "image": "https://cdn2.yopongoelhielo.com/3378-thickbox_default/pepsi.jpg",
      "price": 2.50,
      "quantity": 53
    },
    {
      "id": 2,
      "name": "Sprite",
      "image": "https://www.philpizz.fr/155-thickbox_default/sprite-33-cl.jpg",
      "price": 2.90,
      "quantity": 12
    },
    {
      "id": 3,
      "name": "Oasis",
      "image": "https://cdn.metro-group.com/fr/fr_pim_396932001002_01.png?w=400&h=400&mode=pad",
      "price": 2,
      "quantity": 35
    },
    {
      "id": 4,
      "name": "Ice Tea",
      "image": "https://www.snackmontecarlo.com/wp-content/uploads/2020/03/73.jpg",
      "price": 3,
      "quantity": 68
    }
  ],
  "Dessert": [
    {
      "id": 1,
      "name": "Tiramissu",
      "image": "https://encrypted-tbn0.gstatic.com/images?q=tbn:ANd9GcQRBnKd72f2Y3lMoab5YqKQK6VQ5sffRTlH-XUYQFoSjNZhDkZPNbY2BQuQ3InOivVxK4s&usqp=CAU",
      "price": 3.50,
      "quantity": 12,
      "ingredient": ["café","amareto","oeuf","mascarpone"]
    },
    {
      "id": 2,
      "name": "Brownie",
      "image": "https://encrypted-tbn0.gstatic.com/images?q=tbn:ANd9GcTRYBPN6bGYensz6ku0KWna1jgtienB3ZL633-6cQJPd3gS88z5CxOEGsFn9mKV-QiCZYs&usqp=CAU",
      "price": 3,
      "quantity": 25,
      "ingredient": ["chocolat","farine","oeuf","sucre"]
    },
    {
      "id": 3,
      "name": "Glace",
      "image": "https://assets.afcdn.com/recipe/20150717/10387_w1024h1024c1cx1598cy2321.webp",
      "price": 3.50,
      "quantity": 50,
      "ingredient": ["vanille","fraise","chocolat","noix de coco"]
    }
  ]
}